aablobwrapper/__init__.py
aablobwrapper/wrappers.py
aablobwrapper-0.6.8.dist-info/LICENSE
aablobwrapper-0.6.8.dist-info/METADATA
aablobwrapper-0.6.8.dist-info/WHEEL
aablobwrapper-0.6.8.dist-info/top_level.txt
aablobwrapper-0.6.8.dist-info/RECORD
