Metadata-Version: 2.1
Name: aablobwrapper
Version: 0.6.8
Summary: Provide file-like wrapper for Azure Blobs
Home-page: https://github.com/justdanyul/aablobwrapper
Author: Daniel Kirkegaard Mouritsen
Author-email: daniel.mouritsen@gmail.com
Classifier: Programming Language :: Python :: 3
Classifier: License :: OSI Approved :: MIT License
Classifier: Operating System :: OS Independent
Requires-Python: >=3.7
License-File: LICENSE
Requires-Dist: azure-storage-blob
Requires-Dist: aiohttp
